netcrypt/__init__.py
netcrypt/cli.py
netcrypt/encryptors.py
netcrypt/key_manager.py
netcrypt/sockets.py
netcrypt/tunnel.py
netcryptx-0.1.0.dist-info/licenses/LICENSE
netcryptx-0.1.0.dist-info/METADATA
netcryptx-0.1.0.dist-info/WHEEL
netcryptx-0.1.0.dist-info/top_level.txt
netcryptx-0.1.0.dist-info/RECORD
