Metadata-Version: 2.4
Name: netcryptx
Version: 0.1.0
Summary: Encrypted socket communication and secure tunneling for Python
Author-email: Raghava Chellu <raghava.chellu@gmail.com>
License: MIT
Project-URL: Homepage, https://github.com/RaghavaCh440/netcryptx
Keywords: cryptography,network,socket,encryption,python,vpn,linux
Requires-Python: >=3.7
License-File: LICENSE
Requires-Dist: cryptography>=41.0.0
Requires-Dist: click>=8.0.0
Dynamic: license-file
